{
  "name": "GroveX Tech & Solutions LLC",
  "description": "GroveX Tech & Solutions LLC is a community-rooted B2B growth studio serving Turtle Creek and the Mon Valley. We build practical websites, dependable IT systems, and custom software that help small businesses improve lead flow, strengthen operations, and grow with confidence.",

  "phone": "(412) 206-9453",
  "email": "info@grovextech.com",
  "address": {
    "street": "124 Grant Street",
    "city": "Turtle Creek",
    "state": "PA",
    "zipCode": "15145",
    "country": "United States"
  },
  "hours": [
    {
      "day": "Monday",
      "open": "9:00 AM",
      "close": "5:00 PM"
    },
    {
      "day": "Tuesday", 
      "open": "9:00 AM",
      "close": "5:00 PM"
    },
    {
      "day": "Wednesday",
      "open": "9:00 AM", 
      "close": "5:00 PM"
    },
    {
      "day": "Thursday",
      "open": "9:00 AM",
      "close": "5:00 PM"
    },
    {
      "day": "Friday",
      "open": "9:00 AM",
      "close": "5:00 PM"
    },
    {
      "day": "Saturday",
      "open": "11:00 AM",
      "close": "5:00 PM"
    },
    {
      "day": "Sunday", 
      "open": "11:00 AM",
      "close": "5:00 PM"
    }
  ],
  "socialMedia": {
    "linkedin": "https://www.linkedin.com/company/grovextech/",
    "twitter": "https://x.com/grovextech"
  },
  "foundedYear": 2014,
  "employeeCount": "10-50",
  "specialties": [
    "Custom Software Development",
    "Web Application Development",
    "Mobile App Development",
    "IT Infrastructure Consulting", 
    "Cloud Migration & Strategy",
    "Cybersecurity Assessment",
    "SaaS Product Development",
    "Business Process Automation",
    "Computer Hardware Repair",
    "Data Recovery Services",
    "Network Setup & Maintenance",
    "Technical Support"
  ],
  "tagline": "Websites, systems, and growth foundations for small businesses",
  "mission": "To help local businesses grow with practical websites, stronger systems, and dependable support that improve operations now and create a better foundation for future marketing and customer acquisition.",
  "values": [
    "Business-first thinking: Build what improves outcomes, not just appearances",
    "Technical excellence: Use proven tools and sound implementation",
    "Clear communication: No jargon, just practical advice",
    "Reliable support: Stay useful after the site launches",
    "Local commitment: Help strong local businesses compete better",
    "Sustainable growth: Fix the foundation before scaling spend"
  ]
}
